dexmate_urdf/__init__.py
dexmate_urdf/robots/__init__.py
dexmate_urdf/robots/content.py
dexmate_urdf/robots/paths.py
dexmate_urdf/robots/hands/dexd_gripper/dexd_gripper.urdf
dexmate_urdf/robots/hands/dexd_gripper/meshes/collision/gripper_base.obj
dexmate_urdf/robots/hands/dexd_gripper/meshes/collision/gripper_l1.obj
dexmate_urdf/robots/hands/dexd_gripper/meshes/collision/gripper_l2.obj
dexmate_urdf/robots/hands/dexd_gripper/meshes/visual/gripper_base.glb
dexmate_urdf/robots/hands/dexd_gripper/meshes/visual/gripper_l1.glb
dexmate_urdf/robots/hands/dexd_gripper/meshes/visual/gripper_l2.glb
dexmate_urdf/robots/hands/dexs_gripper/dm_gripper.urdf
dexmate_urdf/robots/hands/dexs_gripper/meshes/collision/gripper_base.obj
dexmate_urdf/robots/hands/dexs_gripper/meshes/collision/gripper_l1.obj
dexmate_urdf/robots/hands/dexs_gripper/meshes/collision/gripper_l2.obj
dexmate_urdf/robots/hands/dexs_gripper/meshes/visual/gripper_base.glb
dexmate_urdf/robots/hands/dexs_gripper/meshes/visual/gripper_l1.glb
dexmate_urdf/robots/hands/dexs_gripper/meshes/visual/gripper_l2.glb
dexmate_urdf/robots/hands/f5d6_hand/f5d6_left.srdf
dexmate_urdf/robots/hands/f5d6_hand/f5d6_left.urdf
dexmate_urdf/robots/hands/f5d6_hand/f5d6_left_collision_spheres.collision.urdf
dexmate_urdf/robots/hands/f5d6_hand/f5d6_right.srdf
dexmate_urdf/robots/hands/f5d6_hand/f5d6_right.urdf
dexmate_urdf/robots/hands/f5d6_hand/f5d6_right_collision_spheres.collision.urdf
dexmate_urdf/robots/hands/f5d6_hand/meshes/collision/L_hand_base.obj
dexmate_urdf/robots/hands/f5d6_hand/meshes/collision/R_hand_base.obj
dexmate_urdf/robots/hands/f5d6_hand/meshes/collision/ff_l1.obj
dexmate_urdf/robots/hands/f5d6_hand/meshes/collision/ff_l2.obj
dexmate_urdf/robots/hands/f5d6_hand/meshes/collision/lf_l1.obj
dexmate_urdf/robots/hands/f5d6_hand/meshes/collision/lf_l2.obj
dexmate_urdf/robots/hands/f5d6_hand/meshes/collision/mf_l1.obj
dexmate_urdf/robots/hands/f5d6_hand/meshes/collision/mf_l2.obj
dexmate_urdf-0.8.0.dist-info/METADATA
dexmate_urdf-0.8.0.dist-info/WHEEL
dexmate_urdf-0.8.0.dist-info/licenses/LICENSE
dexmate_urdf-0.8.0.dist-info/RECORD
