Metadata-Version: 2.4
Name: dexmate-urdf
Version: 0.8.0
Summary: URDF model and tools for Dexmate robots
Project-URL: Repository, https://github.com/dexmate-ai/dexmate-urdf
Author-email: Dexmate <contact@dexmate.ai>
License: Copyright 2025 Dexmate Inc.
License-File: LICENSE
Classifier: Development Status :: 5 - Production/Stable
Classifier: Framework :: Robot Framework :: Library
Classifier: Intended Audience :: Developers
Classifier: Intended Audience :: Science/Research
Classifier: Programming Language :: Python :: 3.10
Classifier: Programming Language :: Python :: 3.11
Classifier: Programming Language :: Python :: 3.12
Classifier: Programming Language :: Python :: 3.13
Classifier: Programming Language :: Python :: 3.14
Classifier: Topic :: Scientific/Engineering
Requires-Python: >=3.10
Provides-Extra: dev
Requires-Dist: pin-pink==3.1.0; extra == 'dev'
Requires-Dist: pin==3.4.0; extra == 'dev'
Requires-Dist: pre-commit; extra == 'dev'
Requires-Dist: pytest; extra == 'dev'
Requires-Dist: qpsolvers[qpalm]; extra == 'dev'
Requires-Dist: sapien==3.0.0b1; extra == 'dev'
Requires-Dist: setuptools; extra == 'dev'
